[
  {
    "public_id": "tenor_pwhrwr",
    "url": "https://res.cloudinary.com/yqmnhcou/image/upload/v1784195386/tenor_pwhrwr.gif",
    "thumb_url": "http://res.cloudinary.com/yqmnhcou/image/upload/c_fill,f_auto,h_200,q_auto,w_200/v1784195386/tenor_pwhrwr",
    "format": "gif",
    "width": 498,
    "height": 268,
    "bytes": 443516,
    "created_at": "2026-07-16T09:49:46Z"
  },
  {
    "public_id": "main-sample",
    "url": "https://res.cloudinary.com/yqmnhcou/image/upload/v1784194349/main-sample.png",
    "thumb_url": "http://res.cloudinary.com/yqmnhcou/image/upload/c_fill,f_auto,h_200,q_auto,w_200/v1784194349/main-sample",
    "format": "png",
    "width": 1248,
    "height": 832,
    "bytes": 1868954,
    "created_at": "2026-07-16T09:32:29Z"
  },
  {
    "public_id": "cld-sample-4",
    "url": "https://res.cloudinary.com/yqmnhcou/image/upload/v1784194349/cld-sample-4.jpg",
    "thumb_url": "http://res.cloudinary.com/yqmnhcou/image/upload/c_fill,f_auto,h_200,q_auto,w_200/v1784194349/cld-sample-4",
    "format": "jpg",
    "width": 1870,
    "height": 1250,
    "bytes": 818600,
    "created_at": "2026-07-16T09:32:29Z"
  },
  {
    "public_id": "cld-sample-5",
    "url": "https://res.cloudinary.com/yqmnhcou/image/upload/v1784194349/cld-sample-5.jpg",
    "thumb_url": "http://res.cloudinary.com/yqmnhcou/image/upload/c_fill,f_auto,h_200,q_auto,w_200/v1784194349/cld-sample-5",
    "format": "jpg",
    "width": 1870,
    "height": 1250,
    "bytes": 379132,
    "created_at": "2026-07-16T09:32:29Z"
  },
  {
    "public_id": "cld-sample-3",
    "url": "https://res.cloudinary.com/yqmnhcou/image/upload/v1784194349/cld-sample-3.jpg",
    "thumb_url": "http://res.cloudinary.com/yqmnhcou/image/upload/c_fill,f_auto,h_200,q_auto,w_200/v1784194349/cld-sample-3",
    "format": "jpg",
    "width": 1870,
    "height": 1250,
    "bytes": 905834,
    "created_at": "2026-07-16T09:32:29Z"
  },
  {
    "public_id": "cld-sample-2",
    "url": "https://res.cloudinary.com/yqmnhcou/image/upload/v1784194348/cld-sample-2.jpg",
    "thumb_url": "http://res.cloudinary.com/yqmnhcou/image/upload/c_fill,f_auto,h_200,q_auto,w_200/v1784194348/cld-sample-2",
    "format": "jpg",
    "width": 1870,
    "height": 1250,
    "bytes": 592235,
    "created_at": "2026-07-16T09:32:28Z"
  },
  {
    "public_id": "cld-sample",
    "url": "https://res.cloudinary.com/yqmnhcou/image/upload/v1784194348/cld-sample.jpg",
    "thumb_url": "http://res.cloudinary.com/yqmnhcou/image/upload/c_fill,f_auto,h_200,q_auto,w_200/v1784194348/cld-sample",
    "format": "jpg",
    "width": 1870,
    "height": 1250,
    "bytes": 476846,
    "created_at": "2026-07-16T09:32:28Z"
  },
  {
    "public_id": "samples/radial_02",
    "url": "https://res.cloudinary.com/yqmnhcou/image/upload/v1784194348/samples/radial_02.png",
    "thumb_url": "http://res.cloudinary.com/yqmnhcou/image/upload/c_fill,f_auto,h_200,q_auto,w_200/v1784194348/samples/radial_02",
    "format": "png",
    "width": 427,
    "height": 271,
    "bytes": 123165,
    "created_at": "2026-07-16T09:32:28Z"
  },
  {
    "public_id": "samples/waves",
    "url": "https://res.cloudinary.com/yqmnhcou/image/upload/v1784194348/samples/waves.png",
    "thumb_url": "http://res.cloudinary.com/yqmnhcou/image/upload/c_fill,f_auto,h_200,q_auto,w_200/v1784194348/samples/waves",
    "format": "png",
    "width": 1024,
    "height": 1024,
    "bytes": 1563444,
    "created_at": "2026-07-16T09:32:28Z"
  },
  {
    "public_id": "samples/paper",
    "url": "https://res.cloudinary.com/yqmnhcou/image/upload/v1784194347/samples/paper.png",
    "thumb_url": "http://res.cloudinary.com/yqmnhcou/image/upload/c_fill,f_auto,h_200,q_auto,w_200/v1784194347/samples/paper",
    "format": "png",
    "width": 1024,
    "height": 1024,
    "bytes": 1440561,
    "created_at": "2026-07-16T09:32:27Z"
  },
  {
    "public_id": "samples/zoom",
    "url": "https://res.cloudinary.com/yqmnhcou/image/upload/v1784194347/samples/zoom.avif",
    "thumb_url": "http://res.cloudinary.com/yqmnhcou/image/upload/c_fill,f_auto,h_200,q_auto,w_200/v1784194347/samples/zoom",
    "format": "avif",
    "width": 484,
    "height": 324,
    "bytes": 2863,
    "created_at": "2026-07-16T09:32:27Z"
  },
  {
    "public_id": "samples/radial",
    "url": "https://res.cloudinary.com/yqmnhcou/image/upload/v1784194347/samples/radial.avif",
    "thumb_url": "http://res.cloudinary.com/yqmnhcou/image/upload/c_fill,f_auto,h_200,q_auto,w_200/v1784194347/samples/radial",
    "format": "avif",
    "width": 950,
    "height": 640,
    "bytes": 4503,
    "created_at": "2026-07-16T09:32:27Z"
  },
  {
    "public_id": "samples/canvas",
    "url": "https://res.cloudinary.com/yqmnhcou/image/upload/v1784194347/samples/canvas.jpg",
    "thumb_url": "http://res.cloudinary.com/yqmnhcou/image/upload/c_fill,f_auto,h_200,q_auto,w_200/v1784194347/samples/canvas",
    "format": "jpg",
    "width": 600,
    "height": 388,
    "bytes": 61928,
    "created_at": "2026-07-16T09:32:27Z"
  },
  {
    "public_id": "samples/logo",
    "url": "https://res.cloudinary.com/yqmnhcou/image/upload/v1784194347/samples/logo.png",
    "thumb_url": "http://res.cloudinary.com/yqmnhcou/image/upload/c_fill,f_auto,h_200,q_auto,w_200/v1784194347/samples/logo",
    "format": "png",
    "width": 480,
    "height": 314,
    "bytes": 10897,
    "created_at": "2026-07-16T09:32:27Z"
  },
  {
    "public_id": "samples/man-portrait",
    "url": "https://res.cloudinary.com/yqmnhcou/image/upload/v1784194345/samples/man-portrait.jpg",
    "thumb_url": "http://res.cloudinary.com/yqmnhcou/image/upload/c_fill,f_auto,h_200,q_auto,w_200/v1784194345/samples/man-portrait",
    "format": "jpg",
    "width": 1333,
    "height": 2000,
    "bytes": 505607,
    "created_at": "2026-07-16T09:32:25Z"
  },
  {
    "public_id": "samples/upscale-face-1",
    "url": "https://res.cloudinary.com/yqmnhcou/image/upload/v1784194347/samples/upscale-face-1.jpg",
    "thumb_url": "http://res.cloudinary.com/yqmnhcou/image/upload/c_fill,f_auto,h_200,q_auto,w_200/v1784194347/samples/upscale-face-1",
    "format": "jpg",
    "width": 233,
    "height": 233,
    "bytes": 18110,
    "created_at": "2026-07-16T09:32:27Z"
  },
  {
    "public_id": "samples/woman-on-a-football-field",
    "url": "https://res.cloudinary.com/yqmnhcou/image/upload/v1784194346/samples/woman-on-a-football-field.jpg",
    "thumb_url": "http://res.cloudinary.com/yqmnhcou/image/upload/c_fill,f_auto,h_200,q_auto,w_200/v1784194346/samples/woman-on-a-football-field",
    "format": "jpg",
    "width": 1200,
    "height": 1350,
    "bytes": 416598,
    "created_at": "2026-07-16T09:32:26Z"
  },
  {
    "public_id": "samples/dessert-on-a-plate",
    "url": "https://res.cloudinary.com/yqmnhcou/image/upload/v1784194346/samples/dessert-on-a-plate.jpg",
    "thumb_url": "http://res.cloudinary.com/yqmnhcou/image/upload/c_fill,f_auto,h_200,q_auto,w_200/v1784194346/samples/dessert-on-a-plate",
    "format": "jpg",
    "width": 1200,
    "height": 1200,
    "bytes": 348717,
    "created_at": "2026-07-16T09:32:26Z"
  },
  {
    "public_id": "samples/cup-on-a-table",
    "url": "https://res.cloudinary.com/yqmnhcou/image/upload/v1784194346/samples/cup-on-a-table.jpg",
    "thumb_url": "http://res.cloudinary.com/yqmnhcou/image/upload/c_fill,f_auto,h_200,q_auto,w_200/v1784194346/samples/cup-on-a-table",
    "format": "jpg",
    "width": 2246,
    "height": 1500,
    "bytes": 134300,
    "created_at": "2026-07-16T09:32:26Z"
  },
  {
    "public_id": "samples/coffee",
    "url": "https://res.cloudinary.com/yqmnhcou/image/upload/v1784194346/samples/coffee.jpg",
    "thumb_url": "http://res.cloudinary.com/yqmnhcou/image/upload/c_fill,f_auto,h_200,q_auto,w_200/v1784194346/samples/coffee",
    "format": "jpg",
    "width": 1920,
    "height": 1280,
    "bytes": 165287,
    "created_at": "2026-07-16T09:32:26Z"
  },
  {
    "public_id": "samples/chair",
    "url": "https://res.cloudinary.com/yqmnhcou/image/upload/v1784194346/samples/chair.png",
    "thumb_url": "http://res.cloudinary.com/yqmnhcou/image/upload/c_fill,f_auto,h_200,q_auto,w_200/v1784194346/samples/chair",
    "format": "png",
    "width": 800,
    "height": 600,
    "bytes": 130488,
    "created_at": "2026-07-16T09:32:26Z"
  },
  {
    "public_id": "samples/chair-and-coffee-table",
    "url": "https://res.cloudinary.com/yqmnhcou/image/upload/v1784194345/samples/chair-and-coffee-table.jpg",
    "thumb_url": "http://res.cloudinary.com/yqmnhcou/image/upload/c_fill,f_auto,h_200,q_auto,w_200/v1784194345/samples/chair-and-coffee-table",
    "format": "jpg",
    "width": 1001,
    "height": 1500,
    "bytes": 64504,
    "created_at": "2026-07-16T09:32:25Z"
  },
  {
    "public_id": "samples/man-on-a-street",
    "url": "https://res.cloudinary.com/yqmnhcou/image/upload/v1784194344/samples/man-on-a-street.jpg",
    "thumb_url": "http://res.cloudinary.com/yqmnhcou/image/upload/c_fill,f_auto,h_200,q_auto,w_200/v1784194344/samples/man-on-a-street",
    "format": "jpg",
    "width": 1340,
    "height": 1340,
    "bytes": 564013,
    "created_at": "2026-07-16T09:32:24Z"
  },
  {
    "public_id": "samples/man-on-a-escalator",
    "url": "https://res.cloudinary.com/yqmnhcou/image/upload/v1784194344/samples/man-on-a-escalator.jpg",
    "thumb_url": "http://res.cloudinary.com/yqmnhcou/image/upload/c_fill,f_auto,h_200,q_auto,w_200/v1784194344/samples/man-on-a-escalator",
    "format": "jpg",
    "width": 1340,
    "height": 1340,
    "bytes": 563708,
    "created_at": "2026-07-16T09:32:24Z"
  },
  {
    "public_id": "samples/outdoor-woman",
    "url": "https://res.cloudinary.com/yqmnhcou/image/upload/v1784194344/samples/outdoor-woman.jpg",
    "thumb_url": "http://res.cloudinary.com/yqmnhcou/image/upload/c_fill,f_auto,h_200,q_auto,w_200/v1784194344/samples/outdoor-woman",
    "format": "jpg",
    "width": 640,
    "height": 963,
    "bytes": 93473,
    "created_at": "2026-07-16T09:32:24Z"
  },
  {
    "public_id": "samples/look-up",
    "url": "https://res.cloudinary.com/yqmnhcou/image/upload/v1784194343/samples/look-up.jpg",
    "thumb_url": "http://res.cloudinary.com/yqmnhcou/image/upload/c_fill,f_auto,h_200,q_auto,w_200/v1784194343/samples/look-up",
    "format": "jpg",
    "width": 900,
    "height": 900,
    "bytes": 414964,
    "created_at": "2026-07-16T09:32:23Z"
  },
  {
    "public_id": "samples/breakfast",
    "url": "https://res.cloudinary.com/yqmnhcou/image/upload/v1784194343/samples/breakfast.jpg",
    "thumb_url": "http://res.cloudinary.com/yqmnhcou/image/upload/c_fill,f_auto,h_200,q_auto,w_200/v1784194343/samples/breakfast",
    "format": "jpg",
    "width": 2447,
    "height": 2196,
    "bytes": 3024938,
    "created_at": "2026-07-16T09:32:23Z"
  },
  {
    "public_id": "samples/smile",
    "url": "https://res.cloudinary.com/yqmnhcou/image/upload/v1784194343/samples/smile.jpg",
    "thumb_url": "http://res.cloudinary.com/yqmnhcou/image/upload/c_fill,f_auto,h_200,q_auto,w_200/v1784194343/samples/smile",
    "format": "jpg",
    "width": 1552,
    "height": 1000,
    "bytes": 657749,
    "created_at": "2026-07-16T09:32:23Z"
  },
  {
    "public_id": "samples/balloons",
    "url": "https://res.cloudinary.com/yqmnhcou/image/upload/v1784194342/samples/balloons.jpg",
    "thumb_url": "http://res.cloudinary.com/yqmnhcou/image/upload/c_fill,f_auto,h_200,q_auto,w_200/v1784194342/samples/balloons",
    "format": "jpg",
    "width": 1000,
    "height": 667,
    "bytes": 117237,
    "created_at": "2026-07-16T09:32:22Z"
  },
  {
    "public_id": "samples/shoe",
    "url": "https://res.cloudinary.com/yqmnhcou/image/upload/v1784194341/samples/shoe.jpg",
    "thumb_url": "http://res.cloudinary.com/yqmnhcou/image/upload/c_fill,f_auto,h_200,q_auto,w_200/v1784194341/samples/shoe",
    "format": "jpg",
    "width": 1000,
    "height": 1140,
    "bytes": 72888,
    "created_at": "2026-07-16T09:32:21Z"
  },
  {
    "public_id": "samples/two-ladies",
    "url": "https://res.cloudinary.com/yqmnhcou/image/upload/v1784194341/samples/two-ladies.jpg",
    "thumb_url": "http://res.cloudinary.com/yqmnhcou/image/upload/c_fill,f_auto,h_200,q_auto,w_200/v1784194341/samples/two-ladies",
    "format": "jpg",
    "width": 1500,
    "height": 1200,
    "bytes": 211712,
    "created_at": "2026-07-16T09:32:21Z"
  },
  {
    "public_id": "samples/landscapes/landscape-panorama",
    "url": "https://res.cloudinary.com/yqmnhcou/image/upload/v1784194339/samples/landscapes/landscape-panorama.jpg",
    "thumb_url": "http://res.cloudinary.com/yqmnhcou/image/upload/c_fill,f_auto,h_200,q_auto,w_200/v1784194339/samples/landscapes/landscape-panorama",
    "format": "jpg",
    "width": 10906,
    "height": 2349,
    "bytes": 7858062,
    "created_at": "2026-07-16T09:32:19Z"
  },
  {
    "public_id": "samples/animals/kitten-playing",
    "url": "https://res.cloudinary.com/yqmnhcou/image/upload/v1784194339/samples/animals/kitten-playing.gif",
    "thumb_url": "http://res.cloudinary.com/yqmnhcou/image/upload/c_fill,f_auto,h_200,q_auto,w_200/v1784194339/samples/animals/kitten-playing",
    "format": "gif",
    "width": 320,
    "height": 180,
    "bytes": 6620002,
    "created_at": "2026-07-16T09:32:19Z"
  },
  {
    "public_id": "samples/landscapes/nature-mountains",
    "url": "https://res.cloudinary.com/yqmnhcou/image/upload/v1784194339/samples/landscapes/nature-mountains.jpg",
    "thumb_url": "http://res.cloudinary.com/yqmnhcou/image/upload/c_fill,f_auto,h_200,q_auto,w_200/v1784194339/samples/landscapes/nature-mountains",
    "format": "jpg",
    "width": 3000,
    "height": 2000,
    "bytes": 3171453,
    "created_at": "2026-07-16T09:32:19Z"
  },
  {
    "public_id": "samples/cloudinary-group",
    "url": "https://res.cloudinary.com/yqmnhcou/image/upload/v1784194338/samples/cloudinary-group.jpg",
    "thumb_url": "http://res.cloudinary.com/yqmnhcou/image/upload/c_fill,f_auto,h_200,q_auto,w_200/v1784194338/samples/cloudinary-group",
    "format": "jpg",
    "width": 3000,
    "height": 1526,
    "bytes": 2856169,
    "created_at": "2026-07-16T09:32:18Z"
  },
  {
    "public_id": "samples/food/spices",
    "url": "https://res.cloudinary.com/yqmnhcou/image/upload/v1784194338/samples/food/spices.jpg",
    "thumb_url": "http://res.cloudinary.com/yqmnhcou/image/upload/c_fill,f_auto,h_200,q_auto,w_200/v1784194338/samples/food/spices",
    "format": "jpg",
    "width": 2000,
    "height": 2000,
    "bytes": 2129950,
    "created_at": "2026-07-16T09:32:18Z"
  },
  {
    "public_id": "samples/imagecon-group",
    "url": "https://res.cloudinary.com/yqmnhcou/image/upload/v1784194338/samples/imagecon-group.jpg",
    "thumb_url": "http://res.cloudinary.com/yqmnhcou/image/upload/c_fill,f_auto,h_200,q_auto,w_200/v1784194338/samples/imagecon-group",
    "format": "jpg",
    "width": 2800,
    "height": 1867,
    "bytes": 1487070,
    "created_at": "2026-07-16T09:32:18Z"
  },
  {
    "public_id": "samples/ecommerce/accessories-bag",
    "url": "https://res.cloudinary.com/yqmnhcou/image/upload/v1784194338/samples/ecommerce/accessories-bag.jpg",
    "thumb_url": "http://res.cloudinary.com/yqmnhcou/image/upload/c_fill,f_auto,h_200,q_auto,w_200/v1784194338/samples/ecommerce/accessories-bag",
    "format": "jpg",
    "width": 3000,
    "height": 2000,
    "bytes": 1459256,
    "created_at": "2026-07-16T09:32:18Z"
  },
  {
    "public_id": "samples/ecommerce/leather-bag-gray",
    "url": "https://res.cloudinary.com/yqmnhcou/image/upload/v1784194337/samples/ecommerce/leather-bag-gray.jpg",
    "thumb_url": "http://res.cloudinary.com/yqmnhcou/image/upload/c_fill,f_auto,h_200,q_auto,w_200/v1784194337/samples/ecommerce/leather-bag-gray",
    "format": "jpg",
    "width": 2385,
    "height": 1590,
    "bytes": 1323582,
    "created_at": "2026-07-16T09:32:17Z"
  },
  {
    "public_id": "samples/ecommerce/car-interior-design",
    "url": "https://res.cloudinary.com/yqmnhcou/image/upload/v1784194337/samples/ecommerce/car-interior-design.jpg",
    "thumb_url": "http://res.cloudinary.com/yqmnhcou/image/upload/c_fill,f_auto,h_200,q_auto,w_200/v1784194337/samples/ecommerce/car-interior-design",
    "format": "jpg",
    "width": 2000,
    "height": 2667,
    "bytes": 1254103,
    "created_at": "2026-07-16T09:32:17Z"
  },
  {
    "public_id": "samples/landscapes/beach-boat",
    "url": "https://res.cloudinary.com/yqmnhcou/image/upload/v1784194337/samples/landscapes/beach-boat.jpg",
    "thumb_url": "http://res.cloudinary.com/yqmnhcou/image/upload/c_fill,f_auto,h_200,q_auto,w_200/v1784194337/samples/landscapes/beach-boat",
    "format": "jpg",
    "width": 2600,
    "height": 1950,
    "bytes": 1235823,
    "created_at": "2026-07-16T09:32:17Z"
  },
  {
    "public_id": "samples/landscapes/architecture-signs",
    "url": "https://res.cloudinary.com/yqmnhcou/image/upload/v1784194336/samples/landscapes/architecture-signs.jpg",
    "thumb_url": "http://res.cloudinary.com/yqmnhcou/image/upload/c_fill,f_auto,h_200,q_auto,w_200/v1784194336/samples/landscapes/architecture-signs",
    "format": "jpg",
    "width": 3000,
    "height": 2000,
    "bytes": 945255,
    "created_at": "2026-07-16T09:32:16Z"
  },
  {
    "public_id": "samples/people/bicycle",
    "url": "https://res.cloudinary.com/yqmnhcou/image/upload/v1784194336/samples/people/bicycle.jpg",
    "thumb_url": "http://res.cloudinary.com/yqmnhcou/image/upload/c_fill,f_auto,h_200,q_auto,w_200/v1784194336/samples/people/bicycle",
    "format": "jpg",
    "width": 2889,
    "height": 1926,
    "bytes": 1130015,
    "created_at": "2026-07-16T09:32:16Z"
  },
  {
    "public_id": "samples/animals/three-dogs",
    "url": "https://res.cloudinary.com/yqmnhcou/image/upload/v1784194336/samples/animals/three-dogs.jpg",
    "thumb_url": "http://res.cloudinary.com/yqmnhcou/image/upload/c_fill,f_auto,h_200,q_auto,w_200/v1784194336/samples/animals/three-dogs",
    "format": "jpg",
    "width": 2700,
    "height": 1800,
    "bytes": 854929,
    "created_at": "2026-07-16T09:32:16Z"
  },
  {
    "public_id": "samples/people/jazz",
    "url": "https://res.cloudinary.com/yqmnhcou/image/upload/v1784194336/samples/people/jazz.jpg",
    "thumb_url": "http://res.cloudinary.com/yqmnhcou/image/upload/c_fill,f_auto,h_200,q_auto,w_200/v1784194336/samples/people/jazz",
    "format": "jpg",
    "width": 3000,
    "height": 1993,
    "bytes": 695548,
    "created_at": "2026-07-16T09:32:16Z"
  },
  {
    "public_id": "samples/people/boy-snow-hoodie",
    "url": "https://res.cloudinary.com/yqmnhcou/image/upload/v1784194336/samples/people/boy-snow-hoodie.jpg",
    "thumb_url": "http://res.cloudinary.com/yqmnhcou/image/upload/c_fill,f_auto,h_200,q_auto,w_200/v1784194336/samples/people/boy-snow-hoodie",
    "format": "jpg",
    "width": 1777,
    "height": 1332,
    "bytes": 581238,
    "created_at": "2026-07-16T09:32:16Z"
  },
  {
    "public_id": "samples/ecommerce/shoes",
    "url": "https://res.cloudinary.com/yqmnhcou/image/upload/v1784194335/samples/ecommerce/shoes.png",
    "thumb_url": "http://res.cloudinary.com/yqmnhcou/image/upload/c_fill,f_auto,h_200,q_auto,w_200/v1784194335/samples/ecommerce/shoes",
    "format": "png",
    "width": 587,
    "height": 507,
    "bytes": 393265,
    "created_at": "2026-07-16T09:32:15Z"
  },
  {
    "public_id": "samples/bike",
    "url": "https://res.cloudinary.com/yqmnhcou/image/upload/v1784194335/samples/bike.jpg",
    "thumb_url": "http://res.cloudinary.com/yqmnhcou/image/upload/c_fill,f_auto,h_200,q_auto,w_200/v1784194335/samples/bike",
    "format": "jpg",
    "width": 2000,
    "height": 1333,
    "bytes": 475687,
    "created_at": "2026-07-16T09:32:15Z"
  },
  {
    "public_id": "samples/sheep",
    "url": "https://res.cloudinary.com/yqmnhcou/image/upload/v1784194335/samples/sheep.jpg",
    "thumb_url": "http://res.cloudinary.com/yqmnhcou/image/upload/c_fill,f_auto,h_200,q_auto,w_200/v1784194335/samples/sheep",
    "format": "jpg",
    "width": 1600,
    "height": 1067,
    "bytes": 269304,
    "created_at": "2026-07-16T09:32:15Z"
  },
  {
    "public_id": "samples/people/smiling-man",
    "url": "https://res.cloudinary.com/yqmnhcou/image/upload/v1784194335/samples/people/smiling-man.jpg",
    "thumb_url": "http://res.cloudinary.com/yqmnhcou/image/upload/c_fill,f_auto,h_200,q_auto,w_200/v1784194335/samples/people/smiling-man",
    "format": "jpg",
    "width": 849,
    "height": 565,
    "bytes": 338794,
    "created_at": "2026-07-16T09:32:15Z"
  },
  {
    "public_id": "samples/landscapes/girl-urban-view",
    "url": "https://res.cloudinary.com/yqmnhcou/image/upload/v1784194335/samples/landscapes/girl-urban-view.jpg",
    "thumb_url": "http://res.cloudinary.com/yqmnhcou/image/upload/c_fill,f_auto,h_200,q_auto,w_200/v1784194335/samples/landscapes/girl-urban-view",
    "format": "jpg",
    "width": 2048,
    "height": 1252,
    "bytes": 372778,
    "created_at": "2026-07-16T09:32:15Z"
  },
  {
    "public_id": "samples/food/pot-mussels",
    "url": "https://res.cloudinary.com/yqmnhcou/image/upload/v1784194334/samples/food/pot-mussels.jpg",
    "thumb_url": "http://res.cloudinary.com/yqmnhcou/image/upload/c_fill,f_auto,h_200,q_auto,w_200/v1784194334/samples/food/pot-mussels",
    "format": "jpg",
    "width": 1220,
    "height": 818,
    "bytes": 191852,
    "created_at": "2026-07-16T09:32:14Z"
  },
  {
    "public_id": "samples/food/fish-vegetables",
    "url": "https://res.cloudinary.com/yqmnhcou/image/upload/v1784194334/samples/food/fish-vegetables.jpg",
    "thumb_url": "http://res.cloudinary.com/yqmnhcou/image/upload/c_fill,f_auto,h_200,q_auto,w_200/v1784194334/samples/food/fish-vegetables",
    "format": "jpg",
    "width": 1220,
    "height": 813,
    "bytes": 169013,
    "created_at": "2026-07-16T09:32:14Z"
  },
  {
    "public_id": "samples/cloudinary-logo-vector",
    "url": "https://res.cloudinary.com/yqmnhcou/image/upload/v1784194333/samples/cloudinary-logo-vector.svg",
    "thumb_url": "http://res.cloudinary.com/yqmnhcou/image/upload/c_fill,f_auto,h_200,q_auto,w_200/v1784194333/samples/cloudinary-logo-vector",
    "format": "svg",
    "width": 1000,
    "height": 320,
    "bytes": 5961,
    "created_at": "2026-07-16T09:32:13Z"
  },
  {
    "public_id": "samples/people/kitchen-bar",
    "url": "https://res.cloudinary.com/yqmnhcou/image/upload/v1784194334/samples/people/kitchen-bar.jpg",
    "thumb_url": "http://res.cloudinary.com/yqmnhcou/image/upload/c_fill,f_auto,h_200,q_auto,w_200/v1784194334/samples/people/kitchen-bar",
    "format": "jpg",
    "width": 1220,
    "height": 813,
    "bytes": 154151,
    "created_at": "2026-07-16T09:32:14Z"
  },
  {
    "public_id": "samples/animals/reindeer",
    "url": "https://res.cloudinary.com/yqmnhcou/image/upload/v1784194334/samples/animals/reindeer.jpg",
    "thumb_url": "http://res.cloudinary.com/yqmnhcou/image/upload/c_fill,f_auto,h_200,q_auto,w_200/v1784194334/samples/animals/reindeer",
    "format": "jpg",
    "width": 1220,
    "height": 813,
    "bytes": 161150,
    "created_at": "2026-07-16T09:32:14Z"
  },
  {
    "public_id": "samples/food/dessert",
    "url": "https://res.cloudinary.com/yqmnhcou/image/upload/v1784194333/samples/food/dessert.jpg",
    "thumb_url": "http://res.cloudinary.com/yqmnhcou/image/upload/c_fill,f_auto,h_200,q_auto,w_200/v1784194333/samples/food/dessert",
    "format": "jpg",
    "width": 1220,
    "height": 813,
    "bytes": 125888,
    "created_at": "2026-07-16T09:32:13Z"
  },
  {
    "public_id": "samples/animals/cat",
    "url": "https://res.cloudinary.com/yqmnhcou/image/upload/v1784194333/samples/animals/cat.jpg",
    "thumb_url": "http://res.cloudinary.com/yqmnhcou/image/upload/c_fill,f_auto,h_200,q_auto,w_200/v1784194333/samples/animals/cat",
    "format": "jpg",
    "width": 768,
    "height": 1024,
    "bytes": 92690,
    "created_at": "2026-07-16T09:32:13Z"
  },
  {
    "public_id": "samples/ecommerce/analog-classic",
    "url": "https://res.cloudinary.com/yqmnhcou/image/upload/v1784194333/samples/ecommerce/analog-classic.jpg",
    "thumb_url": "http://res.cloudinary.com/yqmnhcou/image/upload/c_fill,f_auto,h_200,q_auto,w_200/v1784194333/samples/ecommerce/analog-classic",
    "format": "jpg",
    "width": 1280,
    "height": 853,
    "bytes": 72558,
    "created_at": "2026-07-16T09:32:13Z"
  },
  {
    "public_id": "samples/cloudinary-icon",
    "url": "https://res.cloudinary.com/yqmnhcou/image/upload/v1784194333/samples/cloudinary-icon.png",
    "thumb_url": "http://res.cloudinary.com/yqmnhcou/image/upload/c_fill,f_auto,h_200,q_auto,w_200/v1784194333/samples/cloudinary-icon",
    "format": "png",
    "width": 1000,
    "height": 1000,
    "bytes": 57334,
    "created_at": "2026-07-16T09:32:13Z"
  },
  {
    "public_id": "sample",
    "url": "https://res.cloudinary.com/yqmnhcou/image/upload/v1784194325/sample.jpg",
    "thumb_url": "http://res.cloudinary.com/yqmnhcou/image/upload/c_fill,f_auto,h_200,q_auto,w_200/v1784194325/sample",
    "format": "jpg",
    "width": 864,
    "height": 576,
    "bytes": 120253,
    "created_at": "2026-07-16T09:32:05Z"
  }
]